qsde/__init__.py
qsde/filestore/__init__.py
qsde/filestore/persist.py
qsde-0.1.2.dist-info/WHEEL
qsde-0.1.2.dist-info/METADATA
qsde-0.1.2.dist-info/RECORD
